[
  {
    "hora_utc": "2026-05-17T16:15Z",
    "logo": "img/mlb.png",
    "liga": "MLB",
    "equipos": "Miami Marlins vs Tampa Bay Rays",
    "status": "pronto",
    "canales": [
      {
        "nombre": "2567",
        "url": "https://sharkstreams.net/player.php?channel=2567",
        "calidad": "HD"
      }
    ],
    "fuente": "github"
  },
  {
    "hora_utc": "2026-05-17T17:00Z",
    "logo": "img/nfl.png",
    "liga": "NFL",
    "equipos": "Birmingham Stallions vs Columbus Aviators",
    "status": "pronto",
    "canales": [
      {
        "nombre": "Main Server",
        "url": "https://embedsports.top/embed/admin/ppv-columbus-aviators-vs-birmingham-stallions/1",
        "calidad": "HD"
      }
    ],
    "fuente": "github"
  },
  {
    "hora_utc": "2026-05-17T17:00Z",
    "logo": "img/es.png",
    "liga": "LaLiga",
    "equipos": "Elche vs Getafe",
    "status": "pronto",
    "canales": [
      {
        "nombre": "Main Server",
        "url": "https://embedsports.top/embed/admin/ppv-elche-vs-getafe/1",
        "calidad": "HD"
      }
    ],
    "fuente": "github"
  },
  {
    "hora_utc": "2026-05-17T17:30Z",
    "logo": "img/nba.png",
    "liga": "WNBA",
    "equipos": "Atlanta Dream vs Las Vegas Aces",
    "status": "pronto",
    "canales": [
      {
        "nombre": "2583",
        "url": "https://sharkstreams.net/player.php?channel=2583",
        "calidad": "HD"
      },
      {
        "nombre": "Main Server",
        "url": "https://embedsports.top/embed/admin/ppv-las-vegas-aces-vs-atlanta-dream/1",
        "calidad": "HD"
      },
      {
        "nombre": "Server 2",
        "url": "https://embedsports.top/embed/golf/22430/1",
        "calidad": "HD"
      },
      {
        "nombre": "Server 3",
        "url": "https://embedsports.top/embed/delta/live_wnba_atlanta-las-vegas-live-streaming-1210437351/1",
        "calidad": "HD"
      }
    ],
    "fuente": "github"
  },
  {
    "hora_utc": "2026-05-17T17:35Z",
    "logo": "img/mlb.png",
    "liga": "MLB",
    "equipos": "Atlanta Braves vs Boston Red Sox",
    "status": "pronto",
    "canales": [
      {
        "nombre": "2568",
        "url": "https://sharkstreams.net/player.php?channel=2568",
        "calidad": "HD"
      },
      {
        "nombre": "Main Server",
        "url": "https://embedsports.top/embed/admin/ppv-boston-red-sox-vs-atlanta-braves/1",
        "calidad": "HD"
      },
      {
        "nombre": "Server 2",
        "url": "https://embedsports.top/embed/golf/22436/1",
        "calidad": "HD"
      },
      {
        "nombre": "Server 3",
        "url": "https://embedsports.top/embed/delta/live_mlb_braves-red-sox-live-streaming-1277481240/1",
        "calidad": "HD"
      },
      {
        "nombre": "Server 4",
        "url": "https://embedsports.top/embed/echo/atlanta-braves-vs-boston-red-sox-baseball-178710/1",
        "calidad": "HD"
      }
    ],
    "fuente": "github"
  },
  {
    "hora_utc": "2026-05-17T17:35Z",
    "logo": "img/mlb.png",
    "liga": "MLB",
    "equipos": "Philadelphia Phillies vs Pittsburgh Pirates",
    "status": "pronto",
    "canales": [
      {
        "nombre": "2569",
        "url": "https://sharkstreams.net/player.php?channel=2569",
        "calidad": "HD"
      },
      {
        "nombre": "Main Server",
        "url": "https://embedsports.top/embed/admin/ppv-philadelphia-phillies-vs-pittsburgh-pirates/1",
        "calidad": "HD"
      },
      {
        "nombre": "Server 2",
        "url": "https://embedsports.top/embed/golf/22437/1",
        "calidad": "HD"
      },
      {
        "nombre": "Server 3",
        "url": "https://embedsports.top/embed/delta/live_mlb_pirates-phillies-live-streaming-1277479242/1",
        "calidad": "HD"
      },
      {
        "nombre": "Server 4",
        "url": "https://embedsports.top/embed/echo/pittsburgh-pirates-vs-philadelphia-phillies-baseball-178702/1",
        "calidad": "HD"
      }
    ],
    "fuente": "github"
  },
  {
    "hora_utc": "2026-05-17T17:35Z",
    "logo": "img/mlb.png",
    "liga": "MLB",
    "equipos": "Baltimore Orioles vs Washington Nationals",
    "status": "pronto",
    "canales": [
      {
        "nombre": "2570",
        "url": "https://sharkstreams.net/player.php?channel=2570",
        "calidad": "HD"
      },
      {
        "nombre": "Main Server",
        "url": "https://embedsports.top/embed/admin/ppv-baltimore-orioles-vs-washington-nationals/1",
        "calidad": "HD"
      },
      {
        "nombre": "Server 2",
        "url": "https://embedsports.top/embed/golf/22435/1",
        "calidad": "HD"
      },
      {
        "nombre": "Server 3",
        "url": "https://embedsports.top/embed/delta/live_mlb_nationals-orioles-live-streaming-1277482239/1",
        "calidad": "HD"
      },
      {
        "nombre": "Server 4",
        "url": "https://embedsports.top/embed/echo/washington-nationals-vs-baltimore-orioles-baseball-178698/1",
        "calidad": "HD"
      }
    ],
    "fuente": "github"
  },
  {
    "hora_utc": "2026-05-17T17:40Z",
    "logo": "img/mlb.png",
    "liga": "MLB",
    "equipos": "Cincinnati Reds vs Cleveland Guardians",
    "status": "pronto",
    "canales": [
      {
        "nombre": "2571",
        "url": "https://sharkstreams.net/player.php?channel=2571",
        "calidad": "HD"
      },
      {
        "nombre": "Main Server",
        "url": "https://embedsports.top/embed/admin/ppv-cincinnati-reds-vs-cleveland-guardians/1",
        "calidad": "HD"
      },
      {
        "nombre": "Server 2",
        "url": "https://embedsports.top/embed/golf/22438/1",
        "calidad": "HD"
      },
      {
        "nombre": "Server 3",
        "url": "https://embedsports.top/embed/echo/cleveland-guardians-vs-cincinnati-reds-baseball-178708/1",
        "calidad": "HD"
      }
    ],
    "fuente": "github"
  },
  {
    "hora_utc": "2026-05-17T17:40Z",
    "logo": "img/mlb.png",
    "liga": "MLB",
    "equipos": "Detroit Tigers vs Toronto Blue Jays",
    "status": "pronto",
    "canales": [
      {
        "nombre": "2572",
        "url": "https://sharkstreams.net/player.php?channel=2572",
        "calidad": "HD"
      },
      {
        "nombre": "Main Server",
        "url": "https://embedsports.top/embed/admin/ppv-toronto-blue-jays-vs-detroit-tigers/1",
        "calidad": "HD"
      },
      {
        "nombre": "Server 2",
        "url": "https://embedsports.top/embed/golf/22440/1",
        "calidad": "HD"
      },
      {
        "nombre": "Server 3",
        "url": "https://embedsports.top/embed/delta/live_mlb_tigers-blue-jays-live-streaming-1277484237/1",
        "calidad": "HD"
      },
      {
        "nombre": "Server 4",
        "url": "https://embedsports.top/embed/echo/detroit-tigers-vs-toronto-blue-jays-baseball-178706/1",
        "calidad": "HD"
      }
    ],
    "fuente": "github"
  },
  {
    "hora_utc": "2026-05-17T17:40Z",
    "logo": "img/mlb.png",
    "liga": "MLB",
    "equipos": "New York Mets vs New York Yankees",
    "status": "pronto",
    "canales": [
      {
        "nombre": "2573",
        "url": "https://sharkstreams.net/player.php?channel=2573",
        "calidad": "HD"
      },
      {
        "nombre": "Main Server",
        "url": "https://embedsports.top/embed/admin/ppv-new-york-yankees-vs-new-york-mets/1",
        "calidad": "HD"
      },
      {
        "nombre": "Server 2",
        "url": "https://embedsports.top/embed/golf/22439/1",
        "calidad": "HD"
      },
      {
        "nombre": "Server 3",
        "url": "https://embedsports.top/embed/delta/live_mlb_mets-yankees-live-streaming-1277485236/1",
        "calidad": "HD"
      },
      {
        "nombre": "Server 4",
        "url": "https://embedsports.top/embed/echo/new-york-mets-vs-new-york-yankees-baseball-178703/1",
        "calidad": "HD"
      }
    ],
    "fuente": "github"
  },
  {
    "hora_utc": "2026-05-17T18:10Z",
    "logo": "img/mlb.png",
    "liga": "MLB",
    "equipos": "Kansas City Royals vs St. Louis Cardinals",
    "status": "pronto",
    "canales": [
      {
        "nombre": "2577",
        "url": "https://sharkstreams.net/player.php?channel=2577",
        "calidad": "HD"
      },
      {
        "nombre": "Main Server",
        "url": "https://embedsports.top/embed/admin/ppv-kansas-city-royals-vs-st-louis-cardinals/1",
        "calidad": "HD"
      },
      {
        "nombre": "Server 2",
        "url": "https://embedsports.top/embed/golf/22444/1",
        "calidad": "HD"
      },
      {
        "nombre": "Server 3",
        "url": "https://embedsports.top/embed/delta/live_mlb_cardinals-royals-live-streaming-1277489232/1",
        "calidad": "HD"
      },
      {
        "nombre": "Server 4",
        "url": "https://embedsports.top/embed/echo/stlouis-cardinals-vs-kansas-city-royals-baseball-178700/1",
        "calidad": "HD"
      }
    ],
    "fuente": "github"
  },
  {
    "hora_utc": "2026-05-17T18:10Z",
    "logo": "img/mlb.png",
    "liga": "MLB",
    "equipos": "Milwaukee Brewers vs Minnesota Twins",
    "status": "pronto",
    "canales": [
      {
        "nombre": "2576",
        "url": "https://sharkstreams.net/player.php?channel=2576",
        "calidad": "HD"
      },
      {
        "nombre": "Main Server",
        "url": "https://embedsports.top/embed/admin/ppv-milwaukee-brewers-vs-minnesota-twins/1",
        "calidad": "HD"
      },
      {
        "nombre": "Server 2",
        "url": "https://embedsports.top/embed/golf/22442/1",
        "calidad": "HD"
      },
      {
        "nombre": "Server 3",
        "url": "https://embedsports.top/embed/delta/live_mlb_twins-brewers-live-streaming-1277488233/1",
        "calidad": "HD"
      },
      {
        "nombre": "Server 4",
        "url": "https://embedsports.top/embed/echo/minnesota-twins-vs-milwaukee-brewers-baseball-178697/1",
        "calidad": "HD"
      }
    ],
    "fuente": "github"
  },
  {
    "hora_utc": "2026-05-17T18:10Z",
    "logo": "img/mlb.png",
    "liga": "MLB",
    "equipos": "Houston Astros vs Texas Rangers",
    "status": "pronto",
    "canales": [
      {
        "nombre": "2575",
        "url": "https://sharkstreams.net/player.php?channel=2575",
        "calidad": "HD"
      },
      {
        "nombre": "Main Server",
        "url": "https://embedsports.top/embed/admin/ppv-texas-rangers-vs-houston-astros/1",
        "calidad": "HD"
      },
      {
        "nombre": "Server 2",
        "url": "https://embedsports.top/embed/golf/22443/1",
        "calidad": "HD"
      },
      {
        "nombre": "Server 3",
        "url": "https://embedsports.top/embed/delta/live_mlb_astros-rangers-live-streaming-1277487234/1",
        "calidad": "HD"
      },
      {
        "nombre": "Server 4",
        "url": "https://embedsports.top/embed/echo/houston-astros-vs-texas-rangers-baseball-178704/1",
        "calidad": "HD"
      }
    ],
    "fuente": "github"
  },
  {
    "hora_utc": "2026-05-17T18:10Z",
    "logo": "img/mlb.png",
    "liga": "MLB",
    "equipos": "Chicago Cubs vs Chicago White Sox",
    "status": "pronto",
    "canales": [
      {
        "nombre": "2574",
        "url": "https://sharkstreams.net/player.php?channel=2574",
        "calidad": "HD"
      },
      {
        "nombre": "Main Server",
        "url": "https://embedsports.top/embed/admin/ppv-chicago-cubs-vs-chicago-white-sox/1",
        "calidad": "HD"
      },
      {
        "nombre": "Server 2",
        "url": "https://embedsports.top/embed/golf/22441/1",
        "calidad": "HD"
      },
      {
        "nombre": "Server 3",
        "url": "https://embedsports.top/embed/delta/live_mlb_white-sox-cubs-live-streaming-1277486235/1",
        "calidad": "HD"
      },
      {
        "nombre": "Server 4",
        "url": "https://embedsports.top/embed/echo/chicago-white-sox-vs-chicago-cubs-baseball-178709/1",
        "calidad": "HD"
      }
    ],
    "fuente": "github"
  },
  {
    "hora_utc": "2026-05-17T18:45Z",
    "logo": "img/it.png",
    "liga": "Serie A",
    "equipos": "Cagliari vs Torino",
    "status": "pronto",
    "canales": [
      {
        "nombre": "Main Server",
        "url": "https://embedsports.top/embed/admin/ppv-cagliari-vs-torino/1",
        "calidad": "HD"
      },
      {
        "nombre": "Server 2",
        "url": "https://embedsports.top/embed/delta/live_serie-a_cagliari-torino-live-streaming-1096560342/1",
        "calidad": "HD"
      },
      {
        "nombre": "Server 3",
        "url": "https://embedsports.top/embed/echo/cagliari-vs-torino-football-1378225/1",
        "calidad": "HD"
      }
    ],
    "fuente": "github"
  },
  {
    "hora_utc": "2026-05-17T18:45Z",
    "logo": "img/it.png",
    "liga": "Serie A",
    "equipos": "Lecce vs Sassuolo",
    "status": "pronto",
    "canales": [
      {
        "nombre": "Main Server",
        "url": "https://embedsports.top/embed/admin/ppv-sassuolo-vs-lecce/1",
        "calidad": "HD"
      },
      {
        "nombre": "Server 2",
        "url": "https://embedsports.top/embed/delta/live_serie-a_sassuolo-lecce-live-streaming-1096567335/1",
        "calidad": "HD"
      },
      {
        "nombre": "Server 3",
        "url": "https://embedsports.top/embed/echo/sassuolo-vs-lecce-football-1378232/1",
        "calidad": "HD"
      }
    ],
    "fuente": "github"
  },
  {
    "hora_utc": "2026-05-17T18:45Z",
    "logo": "img/it.png",
    "liga": "Serie A",
    "equipos": "Cremonese vs Udinese",
    "status": "pronto",
    "canales": [
      {
        "nombre": "Main Server",
        "url": "https://embedsports.top/embed/admin/ppv-udinese-vs-cremonese/1",
        "calidad": "HD"
      },
      {
        "nombre": "Server 2",
        "url": "https://embedsports.top/embed/delta/live_serie-a_udinese-cremonese-live-streaming-1096568334/1",
        "calidad": "HD"
      },
      {
        "nombre": "Server 3",
        "url": "https://embedsports.top/embed/echo/udinese-vs-cremonese-football-1378233/1",
        "calidad": "HD"
      }
    ],
    "fuente": "github"
  },
  {
    "hora_utc": "2026-05-17T19:00Z",
    "logo": "img/fr.png",
    "liga": "Ligue 1",
    "equipos": "Angers SCO vs Stade Brestois",
    "status": "pronto",
    "canales": [
      {
        "nombre": "Main Server",
        "url": "https://embedsports.top/embed/admin/ppv-brest-vs-angers/1",
        "calidad": "HD"
      },
      {
        "nombre": "Server 2",
        "url": "https://embedsports.top/embed/echo/stade-brestois-29-vs-angers-football-1387995/1",
        "calidad": "HD"
      }
    ],
    "fuente": "github"
  },
  {
    "hora_utc": "2026-05-17T19:00Z",
    "logo": "img/fr.png",
    "liga": "Ligue 1",
    "equipos": "AJ Auxerre vs LOSC Lille",
    "status": "pronto",
    "canales": [
      {
        "nombre": "Main Server",
        "url": "https://embedsports.top/embed/admin/ppv-lille-vs-aj-auxerre/1",
        "calidad": "HD"
      },
      {
        "nombre": "Server 2",
        "url": "https://embedsports.top/embed/echo/lille-vs-auxerre-football-1387996/1",
        "calidad": "HD"
      }
    ],
    "fuente": "github"
  },
  {
    "hora_utc": "2026-05-17T19:00Z",
    "logo": "img/fr.png",
    "liga": "Ligue 1",
    "equipos": "FC Lorient vs Le Havre AC",
    "status": "pronto",
    "canales": [
      {
        "nombre": "Main Server",
        "url": "https://embedsports.top/embed/admin/ppv-lorient-vs-le-havre-ac/1",
        "calidad": "HD"
      },
      {
        "nombre": "Server 2",
        "url": "https://embedsports.top/embed/echo/lorient-vs-le-havre-football-1387997/1",
        "calidad": "HD"
      }
    ],
    "fuente": "github"
  },
  {
    "hora_utc": "2026-05-17T19:00Z",
    "logo": "img/fr.png",
    "liga": "Ligue 1",
    "equipos": "Olympique Lyonnais vs RC Lens",
    "status": "pronto",
    "canales": [
      {
        "nombre": "Main Server",
        "url": "https://embedsports.top/embed/admin/ppv-lyon-vs-lens/1",
        "calidad": "HD"
      },
      {
        "nombre": "Server 2",
        "url": "https://embedsports.top/embed/echo/lyon-vs-lens-football-1387998/1",
        "calidad": "HD"
      }
    ],
    "fuente": "github"
  },
  {
    "hora_utc": "2026-05-17T19:00Z",
    "logo": "img/fr.png",
    "liga": "Ligue 1",
    "equipos": "Olympique de Marseille vs Stade Rennais",
    "status": "pronto",
    "canales": [
      {
        "nombre": "Main Server",
        "url": "https://embedsports.top/embed/echo/marseille-vs-rennes-football-1387999/1",
        "calidad": "HD"
      }
    ],
    "fuente": "github"
  },
  {
    "hora_utc": "2026-05-17T19:00Z",
    "logo": "img/fr.png",
    "liga": "Ligue 1",
    "equipos": "FC Nantes vs Toulouse FC",
    "status": "pronto",
    "canales": [
      {
        "nombre": "Main Server",
        "url": "https://embedsports.top/embed/admin/ppv-nantes-vs-toulouse/1",
        "calidad": "HD"
      }
    ],
    "fuente": "github"
  },
  {
    "hora_utc": "2026-05-17T19:00Z",
    "logo": "img/fr.png",
    "liga": "Ligue 1",
    "equipos": "FC Metz vs OGC Nice",
    "status": "pronto",
    "canales": [
      {
        "nombre": "Main Server",
        "url": "https://embedsports.top/embed/admin/ppv-nice-vs-metz/1",
        "calidad": "HD"
      },
      {
        "nombre": "Server 2",
        "url": "https://embedsports.top/embed/echo/nice-vs-metz-football-1388001/1",
        "calidad": "HD"
      }
    ],
    "fuente": "github"
  },
  {
    "hora_utc": "2026-05-17T19:00Z",
    "logo": "img/default.png",
    "liga": "Soccer",
    "equipos": "Paris vs Paris Saint-Germain",
    "status": "pronto",
    "canales": [
      {
        "nombre": "Main Server",
        "url": "https://embedsports.top/embed/admin/ppv-paris-fc-vs-paris-saint-germain/1",
        "calidad": "HD"
      },
      {
        "nombre": "Server 2",
        "url": "https://embedsports.top/embed/echo/paris-fc-vs-paris-saint-germain-football-1388002/1",
        "calidad": "HD"
      }
    ],
    "fuente": "github"
  },
  {
    "hora_utc": "2026-05-17T19:00Z",
    "logo": "img/fr.png",
    "liga": "Ligue 1",
    "equipos": "AS Monaco vs RC Strasbourg",
    "status": "pronto",
    "canales": [
      {
        "nombre": "Main Server",
        "url": "https://embedsports.top/embed/admin/ppv-strasbourg-vs-as-monaco/1",
        "calidad": "HD"
      },
      {
        "nombre": "Server 2",
        "url": "https://embedsports.top/embed/echo/strasbourg-vs-monaco-football-1388003/1",
        "calidad": "HD"
      }
    ],
    "fuente": "github"
  },
  {
    "hora_utc": "2026-05-17T19:10Z",
    "logo": "img/mlb.png",
    "liga": "MLB",
    "equipos": "Arizona Diamondbacks vs Colorado Rockies",
    "status": "pronto",
    "canales": [
      {
        "nombre": "2578",
        "url": "https://sharkstreams.net/player.php?channel=2578",
        "calidad": "HD"
      },
      {
        "nombre": "Main Server",
        "url": "https://embedsports.top/embed/admin/ppv-arizona-diamondbacks-vs-colorado-rockies/1",
        "calidad": "HD"
      },
      {
        "nombre": "Server 2",
        "url": "https://embedsports.top/embed/golf/22445/1",
        "calidad": "HD"
      },
      {
        "nombre": "Server 3",
        "url": "https://embedsports.top/embed/delta/live_mlb_rockies-diamondbacks-live-streaming-1277490231/1",
        "calidad": "HD"
      }
    ],
    "fuente": "github"
  },
  {
    "hora_utc": "2026-05-17T19:15Z",
    "logo": "img/es.png",
    "liga": "LaLiga",
    "equipos": "Barcelona SC vs Real Betis",
    "status": "pronto",
    "canales": [
      {
        "nombre": "Main Server",
        "url": "https://embedsports.top/embed/admin/ppv-barcelona-vs-real-betis/1",
        "calidad": "HD"
      },
      {
        "nombre": "Server 2",
        "url": "https://embedsports.top/embed/golf/22467/1",
        "calidad": "HD"
      },
      {
        "nombre": "Server 3",
        "url": "https://embedsports.top/embed/delta/live_laliga_barcelona-real-betis-live-streaming-1096571331/1",
        "calidad": "HD"
      },
      {
        "nombre": "Server 4",
        "url": "https://embedsports.top/embed/echo/barcelona-vs-real-betis-football-1391181/1",
        "calidad": "HD"
      }
    ],
    "fuente": "github"
  },
  {
    "hora_utc": "2026-05-17T19:55:00Z",
    "logo": "img/default.png",
    "liga": "Deportes",
    "equipos": "Premier Padel Buenos Aires – Final Masculina",
    "status": "pronto",
    "canales": [
      {
        "nombre": "ESPN 4",
        "url": "https://tvtvhd.com/canales.php?stream=espn4",
        "calidad": "HD"
      },
      {
        "nombre": "ESPN 4 | OP2",
        "url": "https://tvtvhd.com/vivo/canal.php?stream=espn4",
        "calidad": "HD"
      },
      {
        "nombre": "ESPN 4 | OP3",
        "url": "https://tvtvhd.com/vivo/canales.php?stream=espn4",
        "calidad": "HD"
      }
    ],
    "fuente": "pltvhd"
  },
  {
    "hora_utc": "2026-05-17T20:00:00Z",
    "logo": "img/bo.png",
    "liga": "Primera División",
    "equipos": "Sportivo Luqueño vs Sportivo San Lorenzo",
    "status": "pronto",
    "canales": [
      {
        "nombre": "fanatiz 07",
        "url": "https://tvtvhd.com/vivo/canales.php?stream=fanatiz7",
        "calidad": "HD"
      }
    ],
    "fuente": "pltvhd"
  },
  {
    "hora_utc": "2026-05-17T20:00:00Z",
    "logo": "img/ar.png",
    "liga": "Liga Profesional",
    "equipos": "Argentinos Juniors vs Belgrano",
    "status": "pronto",
    "canales": [
      {
        "nombre": "ESPN",
        "url": "https://tvtvhd.com/canales.php?stream=espn",
        "calidad": "HD"
      },
      {
        "nombre": "ESPN AR┃OP2",
        "url": "https://tvtvhd.com/vivo/canal.php?stream=espn",
        "calidad": "HD"
      },
      {
        "nombre": "ESPN AR┃OP3",
        "url": "https://tvtvhd.com/vivo/canales.php?stream=espn",
        "calidad": "HD"
      },
      {
        "nombre": "Disney+",
        "url": "https://tvtvhd.com/canales.php?stream=disney6",
        "calidad": "HD"
      },
      {
        "nombre": "Disney+",
        "url": "https://tvtvhd.com/canales.php?stream=disney8",
        "calidad": "HD"
      },
      {
        "nombre": "TNT Sports",
        "url": "https://tvtvhd.com/canales.php?stream=tntsports",
        "calidad": "HD"
      },
      {
        "nombre": "TNT Sports | OP2",
        "url": "https://tvtvhd.com/canales.php?stream=tntsports",
        "calidad": "HD"
      },
      {
        "nombre": "TNT Sports | OP3",
        "url": "https://tvtvhd.com/canales.php?stream=tntsports",
        "calidad": "HD"
      },
      {
        "nombre": "ESPN Premium",
        "url": "https://tvtvhd.com/vivo/canal.php?stream=espnpremium",
        "calidad": "HD"
      },
      {
        "nombre": "ESPN Premium┃OP2",
        "url": "https://tvtvhd.com/vivo/canal.php?stream=espnpremium",
        "calidad": "HD"
      },
      {
        "nombre": "ESPN Premium┃OP3",
        "url": "https://tvtvhd.com/vivo/canales.php?stream=espnpremium",
        "calidad": "HD"
      }
    ],
    "fuente": "pltvhd"
  },
  {
    "hora_utc": "2026-05-17T20:05Z",
    "logo": "img/mlb.png",
    "liga": "MLB",
    "equipos": "Athletics vs San Francisco Giants",
    "status": "pronto",
    "canales": [
      {
        "nombre": "2579",
        "url": "https://sharkstreams.net/player.php?channel=2579",
        "calidad": "HD"
      },
      {
        "nombre": "Main Server",
        "url": "https://embedsports.top/embed/admin/ppv-san-francisco-giants-vs-athletics/1",
        "calidad": "HD"
      },
      {
        "nombre": "Server 2",
        "url": "https://embedsports.top/embed/golf/22446/1",
        "calidad": "HD"
      },
      {
        "nombre": "Server 3",
        "url": "https://embedsports.top/embed/delta/live_mlb_athletics-giants-live-streaming-1277491230/1",
        "calidad": "HD"
      }
    ],
    "fuente": "github"
  },
  {
    "hora_utc": "2026-05-17T20:07Z",
    "logo": "img/mlb.png",
    "liga": "MLB",
    "equipos": "Los Angeles Angels vs Los Angeles Dodgers",
    "status": "pronto",
    "canales": [
      {
        "nombre": "2580",
        "url": "https://sharkstreams.net/player.php?channel=2580",
        "calidad": "HD"
      },
      {
        "nombre": "Main Server",
        "url": "https://embedsports.top/embed/admin/ppv-los-angeles-dodgers-vs-los-angeles-angels/1",
        "calidad": "HD"
      },
      {
        "nombre": "Server 2",
        "url": "https://embedsports.top/embed/golf/22447/1",
        "calidad": "HD"
      },
      {
        "nombre": "Server 3",
        "url": "https://embedsports.top/embed/delta/live_mlb_angels-dodgers-live-streaming-1277492229/1",
        "calidad": "HD"
      }
    ],
    "fuente": "github"
  },
  {
    "hora_utc": "2026-05-17T20:30:00Z",
    "logo": "img/pe.png",
    "liga": "Liga1",
    "equipos": "Deportivo Moquegua vs Los Chankas",
    "status": "pronto",
    "canales": [
      {
        "nombre": "Liga1MAX",
        "url": "https://tvtvhd.com/vivo/canal.php?stream=liga1max",
        "calidad": "HD"
      },
      {
        "nombre": "Liga1Max | OP2",
        "url": "https://tvtvhd.com/vivo/canal.php?stream=liga1max",
        "calidad": "HD"
      },
      {
        "nombre": "Liga1Max | OP3",
        "url": "https://tvtvhd.com/vivo/canales.php?stream=liga1max",
        "calidad": "HD"
      }
    ],
    "fuente": "pltvhd"
  },
  {
    "hora_utc": "2026-05-17T21:00:00Z",
    "logo": "img/uy.png",
    "liga": "Liga AUF Uruguaya",
    "equipos": "Albion FC vs Montevideo Wanderers",
    "status": "pronto",
    "canales": [
      {
        "nombre": "Disney+",
        "url": "https://tvtvhd.com/canales.php?stream=disney7",
        "calidad": "HD"
      }
    ],
    "fuente": "pltvhd"
  },
  {
    "hora_utc": "2026-05-17T21:30:00Z",
    "logo": "img/br.png",
    "liga": "Brasilerao",
    "equipos": "RB Bragantino vs Vitória",
    "status": "pronto",
    "canales": [
      {
        "nombre": "Premiere BR ",
        "url": "https://tvtvhd.com/canales.php?stream=premiere1",
        "calidad": "HD"
      },
      {
        "nombre": "fanatiz 09",
        "url": "https://tvtvhd.com/vivo/canales.php?stream=fanatiz9",
        "calidad": "HD"
      }
    ],
    "fuente": "pltvhd"
  },
  {
    "hora_utc": "2026-05-17T21:30:00Z",
    "logo": "img/bo.png",
    "liga": "Primera División",
    "equipos": "Colo-Colo vs Ñublense",
    "status": "pronto",
    "canales": [
      {
        "nombre": "TNT Sports Premiun CL",
        "url": "https://tvtvhd.com/canales.php?stream=tntsportschile",
        "calidad": "HD"
      },
      {
        "nombre": "TNT Sports Premiun CL OP2",
        "url": "https://tvtvhd.com/canales.php?stream=tntsportschile",
        "calidad": "HD"
      }
    ],
    "fuente": "pltvhd"
  },
  {
    "hora_utc": "2026-05-17T21:30:00Z",
    "logo": "img/br.png",
    "liga": "Brasileirão",
    "equipos": "Chapecoense vs Remo",
    "status": "pronto",
    "canales": [
      {
        "nombre": "Premiere 5 BR ",
        "url": "https://tvtvhd.com/canales.php?stream=premiere5",
        "calidad": "HD"
      },
      {
        "nombre": "Fanatiz 10",
        "url": "https://tvtvhd.com/canales.php?stream=fanatiz10",
        "calidad": "HD"
      }
    ],
    "fuente": "pltvhd"
  },
  {
    "hora_utc": "2026-05-17T22:00:00Z",
    "logo": "img/default.png",
    "liga": "Primera B",
    "equipos": "Barranquilla vs Unión Magdalena",
    "status": "pronto",
    "canales": [
      {
        "nombre": "Win Sports +",
        "url": "https://tvtvhd.com/vivo/canal.php?stream=winsportsplus",
        "calidad": "HD"
      },
      {
        "nombre": "Win Sports + | OP2",
        "url": "https://tvtvhd.com/vivo/canal.php?stream=winsportsplus",
        "calidad": "HD"
      },
      {
        "nombre": "Win Sports + | OP3",
        "url": "https://tvtvhd.com/vivo/canales.php?stream=winsportsplus",
        "calidad": "HD"
      }
    ],
    "fuente": "pltvhd"
  },
  {
    "hora_utc": "2026-05-17T22:00:00Z",
    "logo": "img/usa.png",
    "liga": "MLS",
    "equipos": "Inter Miami vs Portland Timbers",
    "status": "pronto",
    "canales": [
      {
        "nombre": "MLS 01 | EN",
        "url": "https://tvtvhd.com/canales.php?stream=mls1en",
        "calidad": "HD"
      },
      {
        "nombre": "Main Server",
        "url": "https://embedsports.top/embed/admin/ppv-inter-miami-cf-vs-portland-timbers/1",
        "calidad": "HD"
      },
      {
        "nombre": "Server 2",
        "url": "https://embedsports.top/embed/golf/22492/1",
        "calidad": "HD"
      }
    ],
    "fuente": "pltvhd"
  },
  {
    "hora_utc": "2026-05-17T22:00Z",
    "logo": "img/nba.png",
    "liga": "WNBA",
    "equipos": "Indiana Fever vs Seattle Storm",
    "status": "pronto",
    "canales": [
      {
        "nombre": "2584",
        "url": "https://sharkstreams.net/player.php?channel=2584",
        "calidad": "HD"
      },
      {
        "nombre": "Main Server",
        "url": "https://embedsports.top/embed/admin/ppv-seattle-storm-vs-indiana-fever/1",
        "calidad": "HD"
      },
      {
        "nombre": "Server 2",
        "url": "https://embedsports.top/embed/golf/22431/1",
        "calidad": "HD"
      },
      {
        "nombre": "Server 3",
        "url": "https://embedsports.top/embed/delta/live_wnba_fever-storm-live-streaming-1210438350/1",
        "calidad": "HD"
      }
    ],
    "fuente": "github"
  },
  {
    "hora_utc": "2026-05-17T22:30:00Z",
    "logo": "img/br.png",
    "liga": "Brasilerao",
    "equipos": "Athletico Paranaense vs Flamengo",
    "status": "pronto",
    "canales": [
      {
        "nombre": "Sportv BR",
        "url": "https://tvtvhd.com/vivo/canales.php?stream=sportv",
        "calidad": "HD"
      },
      {
        "nombre": "Premiere 4 BR ",
        "url": "https://tvtvhd.com/canales.php?stream=premiere4",
        "calidad": "HD"
      },
      {
        "nombre": "fanatiz 01",
        "url": "https://tvtvhd.com/canales.php?stream=fanatiz1",
        "calidad": "HD"
      },
      {
        "nombre": "Win Sports",
        "url": "https://tvtvhd.com/vivo/canal.php?stream=winsports",
        "calidad": "HD"
      },
      {
        "nombre": "Win Sports | OP2",
        "url": "https://tvtvhd.com/vivo/canal.php?stream=winsports",
        "calidad": "HD"
      },
      {
        "nombre": "Win Sports ┃OP3",
        "url": "https://tvtvhd.com/vivo/canales.php?stream=winsports",
        "calidad": "HD"
      }
    ],
    "fuente": "pltvhd"
  },
  {
    "hora_utc": "2026-05-17T23:00:00Z",
    "logo": "img/mlb.png",
    "liga": "MLB",
    "equipos": "San Diego Padres vs Seattle Mariners",
    "status": "pronto",
    "canales": [
      {
        "nombre": "ESPN 2",
        "url": "https://tvtvhd.com/canales.php?stream=espn2",
        "calidad": "HD"
      },
      {
        "nombre": "ESPN 2 | OP2",
        "url": "https://tvtvhd.com/vivo/canal.php?stream=espn2",
        "calidad": "HD"
      },
      {
        "nombre": "ESPN 2 | OP3",
        "url": "https://tvtvhd.com/vivo/canales.php?stream=espn2",
        "calidad": "HD"
      },
      {
        "nombre": "2581",
        "url": "https://sharkstreams.net/player.php?channel=2581",
        "calidad": "HD"
      },
      {
        "nombre": "Main Server",
        "url": "https://embedsports.top/embed/admin/ppv-san-diego-padres-vs-seattle-mariners/1",
        "calidad": "HD"
      },
      {
        "nombre": "Server 2",
        "url": "https://embedsports.top/embed/golf/22448/1",
        "calidad": "HD"
      }
    ],
    "fuente": "pltvhd"
  },
  {
    "hora_utc": "2026-05-17T23:00Z",
    "logo": "img/nba.png",
    "liga": "WNBA",
    "equipos": "Chicago Sky vs Minnesota Lynx",
    "status": "pronto",
    "canales": [
      {
        "nombre": "2585",
        "url": "https://sharkstreams.net/player.php?channel=2585",
        "calidad": "HD"
      },
      {
        "nombre": "Main Server",
        "url": "https://embedsports.top/embed/admin/ppv-chicago-sky-vs-minnesota-lynx/1",
        "calidad": "HD"
      },
      {
        "nombre": "Server 2",
        "url": "https://embedsports.top/embed/golf/22432/1",
        "calidad": "HD"
      }
    ],
    "fuente": "github"
  },
  {
    "hora_utc": "2026-05-17T23:00Z",
    "logo": "img/nba.png",
    "liga": "WNBA",
    "equipos": "Los Angeles Sparks vs Toronto Tempo",
    "status": "pronto",
    "canales": [
      {
        "nombre": "2586",
        "url": "https://sharkstreams.net/player.php?channel=2586",
        "calidad": "HD"
      },
      {
        "nombre": "Main Server",
        "url": "https://embedsports.top/embed/admin/ppv-toronto-tempo-vs-los-angeles-sparks/1",
        "calidad": "HD"
      },
      {
        "nombre": "Server 2",
        "url": "https://embedsports.top/embed/golf/22433/1",
        "calidad": "HD"
      }
    ],
    "fuente": "github"
  },
  {
    "hora_utc": "2026-05-17T23:10:00Z",
    "logo": "img/ec.png",
    "liga": "Liga Pro",
    "equipos": "Emelec vs Manta FC",
    "status": "pronto",
    "canales": [
      {
        "nombre": "ECDF LigaPro",
        "url": "https://tvtvhd.com/canales.php?stream=ecdf_ligapro",
        "calidad": "HD"
      }
    ],
    "fuente": "pltvhd"
  },
  {
    "hora_utc": "2026-05-17T23:30:00Z",
    "logo": "img/bo.png",
    "liga": "Primera División",
    "equipos": "Guabirá vs Nacional Potosí",
    "status": "pronto",
    "canales": [
      {
        "nombre": "Futbol Canal",
        "url": "https://tvtvhd.com/tv/canal.php?stream=even1",
        "calidad": "HD"
      },
      {
        "nombre": "Futbol Canal | OP2",
        "url": "https://tvtvhd.com/tv/canal.php?stream=even1",
        "calidad": "HD"
      },
      {
        "nombre": "Futbol Canal | OP3",
        "url": "https://tvtvhd.com/tv/canal.php?stream=even1",
        "calidad": "HD"
      }
    ],
    "fuente": "pltvhd"
  },
  {
    "hora_utc": "2026-05-17T23:30:00Z",
    "logo": "img/default.png",
    "liga": "Segunda División",
    "equipos": "La Luz vs Oriental",
    "status": "pronto",
    "canales": [
      {
        "nombre": "Disney+",
        "url": "https://tvtvhd.com/canales.php?stream=disney8",
        "calidad": "HD"
      }
    ],
    "fuente": "pltvhd"
  },
  {
    "hora_utc": "2026-05-18T00:00:00Z",
    "logo": "img/cl.png",
    "liga": "Liga de Primera",
    "equipos": "Deportes Concepción vs Everton",
    "status": "pronto",
    "canales": [
      {
        "nombre": "TNT Sports Premiun CL",
        "url": "https://tvtvhd.com/canales.php?stream=tntsportschile",
        "calidad": "HD"
      },
      {
        "nombre": "TNT Sports Premiun CL OP2",
        "url": "https://tvtvhd.com/canales.php?stream=tntsportschile",
        "calidad": "HD"
      }
    ],
    "fuente": "pltvhd"
  },
  {
    "hora_utc": "2026-05-18T00:00Z",
    "logo": "img/nba.png",
    "liga": "NBA",
    "equipos": "Cleveland Cavaliers vs Detroit Pistons",
    "status": "pronto",
    "canales": [
      {
        "nombre": "2582",
        "url": "https://sharkstreams.net/player.php?channel=2582",
        "calidad": "HD"
      },
      {
        "nombre": "Main Server",
        "url": "https://embedsports.top/embed/admin/ppv-cleveland-cavaliers-vs-detroit-pistons/1",
        "calidad": "HD"
      },
      {
        "nombre": "Server 2",
        "url": "https://embedsports.top/embed/golf/22429/1",
        "calidad": "HD"
      }
    ],
    "fuente": "github"
  },
  {
    "hora_utc": "2026-05-18T00:40:00Z",
    "logo": "img/default.png",
    "liga": "Primera B",
    "equipos": "Bogotá vs Real Cartagena",
    "status": "pronto",
    "canales": [
      {
        "nombre": "Win Sports +",
        "url": "https://tvtvhd.com/vivo/canal.php?stream=winsportsplus",
        "calidad": "HD"
      },
      {
        "nombre": "Win Sports + | OP2",
        "url": "https://tvtvhd.com/vivo/canal.php?stream=winsportsplus",
        "calidad": "HD"
      },
      {
        "nombre": "Win Sports + | OP3",
        "url": "https://tvtvhd.com/vivo/canales.php?stream=winsportsplus",
        "calidad": "HD"
      }
    ],
    "fuente": "pltvhd"
  },
  {
    "hora_utc": "2026-05-18T01:00:00Z",
    "logo": "img/mx.png",
    "liga": "Liga MX",
    "equipos": "Pachuca vs Pumas UNAM",
    "status": "pronto",
    "canales": [
      {
        "nombre": "Canal 5 MX",
        "url": "https://tvtvhd.com/canales.php?stream=canal5",
        "calidad": "HD"
      },
      {
        "nombre": "Azteca 7",
        "url": "https://tvtvhd.com/canales.php?stream=azteca7",
        "calidad": "HD"
      },
      {
        "nombre": "Azteca 7 | OP2",
        "url": "https://tvtvhd.com/vivo/canal.php?stream=azteca7",
        "calidad": "HD"
      },
      {
        "nombre": "Azteca 7 | OP3",
        "url": "https://tvtvhd.com/vivo/canales.php?stream=azteca7",
        "calidad": "HD"
      },
      {
        "nombre": "TUDN USA",
        "url": "https://tvtvhd.com/canales.php?stream=tudn",
        "calidad": "HD"
      },
      {
        "nombre": "TUDN USA | OP2",
        "url": "https://tvtvhd.com/vivo/canal.php?stream=tudn",
        "calidad": "HD"
      },
      {
        "nombre": "TUDN USA | OP3",
        "url": "https://tvtvhd.com/vivo/canales.php?stream=tudn",
        "calidad": "HD"
      },
      {
        "nombre": "Univision USA",
        "url": "https://tvtvhd.com/canales.php?stream=univision",
        "calidad": "HD"
      }
    ],
    "fuente": "pltvhd"
  },
  {
    "hora_utc": "2026-05-18T19:00Z",
    "logo": "img/en.png",
    "liga": "Premier League",
    "equipos": "Arsenal vs Burnley",
    "status": "pronto",
    "canales": [
      {
        "nombre": "Main Server",
        "url": "https://embedsports.top/embed/admin/ppv-arsenal-vs-burnley/1",
        "calidad": "HD"
      },
      {
        "nombre": "Server 2",
        "url": "https://embedsports.top/embed/golf/22428/1",
        "calidad": "HD"
      }
    ],
    "fuente": "github"
  },
  {
    "hora_utc": "2026-05-18T22:40Z",
    "logo": "img/mlb.png",
    "liga": "MLB",
    "equipos": "Baltimore Orioles vs Tampa Bay Rays",
    "status": "pronto",
    "canales": [
      {
        "nombre": "Main Server",
        "url": "https://embedsports.top/embed/golf/22474/1",
        "calidad": "HD"
      }
    ],
    "fuente": "github"
  },
  {
    "hora_utc": "2026-05-18T22:45Z",
    "logo": "img/mlb.png",
    "liga": "MLB",
    "equipos": "New York Mets vs Washington Nationals",
    "status": "pronto",
    "canales": [
      {
        "nombre": "Main Server",
        "url": "https://embedsports.top/embed/golf/22477/1",
        "calidad": "HD"
      }
    ],
    "fuente": "github"
  },
  {
    "hora_utc": "2026-05-18T23:05Z",
    "logo": "img/mlb.png",
    "liga": "MLB",
    "equipos": "New York Yankees vs Toronto Blue Jays",
    "status": "pronto",
    "canales": [
      {
        "nombre": "Main Server",
        "url": "https://embedsports.top/embed/golf/22478/1",
        "calidad": "HD"
      }
    ],
    "fuente": "github"
  }
]